{
  "companyName": "Raymond-Greene",
  "description": "Create politics wait writer. Image also still low task.\nHimself gas yeah one. Market carry enough lot one speech spring message. Certain maintain happen allow church. Skin her reveal citizen than start.",
  "dailyStockPrice": [
    {
      "date": "2024-06-21",
      "price": 89.85
    },
    {
      "date": "2024-06-22",
      "price": 88.8
    },
    {
      "date": "2024-06-23",
      "price": 87.68
    },
    {
      "date": "2024-06-24",
      "price": 86.37
    },
    {
      "date": "2024-06-25",
      "price": 86.62
    },
    {
      "date": "2024-06-26",
      "price": 88.59
    },
    {
      "date": "2024-06-27",
      "price": 88.81
    },
    {
      "date": "2024-06-28",
      "price": 89.14
    },
    {
      "date": "2024-06-29",
      "price": 87.58
    },
    {
      "date": "2024-06-30",
      "price": 87.62
    },
    {
      "date": "2024-07-01",
      "price": 88.12
    },
    {
      "date": "2024-07-02",
      "price": 86.85
    },
    {
      "date": "2024-07-03",
      "price": 86.27
    },
    {
      "date": "2024-07-04",
      "price": 86.14
    },
    {
      "date": "2024-07-05",
      "price": 86.7
    },
    {
      "date": "2024-07-06",
      "price": 87.25
    },
    {
      "date": "2024-07-07",
      "price": 86.46
    },
    {
      "date": "2024-07-08",
      "price": 86.03
    },
    {
      "date": "2024-07-09",
      "price": 86.62
    },
    {
      "date": "2024-07-10",
      "price": 85.03
    },
    {
      "date": "2024-07-11",
      "price": 85.9
    },
    {
      "date": "2024-07-12",
      "price": 86.83
    },
    {
      "date": "2024-07-13",
      "price": 85.68
    },
    {
      "date": "2024-07-14",
      "price": 87.61
    },
    {
      "date": "2024-07-15",
      "price": 86.8
    },
    {
      "date": "2024-07-16",
      "price": 86.48
    },
    {
      "date": "2024-07-17",
      "price": 87.12
    },
    {
      "date": "2024-07-18",
      "price": 86.05
    },
    {
      "date": "2024-07-19",
      "price": 84.86
    },
    {
      "date": "2024-07-20",
      "price": 86.14
    },
    {
      "date": "2024-07-21",
      "price": 86.77
    },
    {
      "date": "2024-07-22",
      "price": 85.97
    },
    {
      "date": "2024-07-23",
      "price": 85.21
    },
    {
      "date": "2024-07-24",
      "price": 85.38
    },
    {
      "date": "2024-07-25",
      "price": 85.0
    },
    {
      "date": "2024-07-26",
      "price": 85.4
    },
    {
      "date": "2024-07-27",
      "price": 87.19
    },
    {
      "date": "2024-07-28",
      "price": 87.54
    },
    {
      "date": "2024-07-29",
      "price": 87.34
    },
    {
      "date": "2024-07-30",
      "price": 86.64
    },
    {
      "date": "2024-07-31",
      "price": 86.41
    },
    {
      "date": "2024-08-01",
      "price": 87.78
    },
    {
      "date": "2024-08-02",
      "price": 88.2
    },
    {
      "date": "2024-08-03",
      "price": 89.69
    },
    {
      "date": "2024-08-04",
      "price": 90.88
    },
    {
      "date": "2024-08-05",
      "price": 89.59
    },
    {
      "date": "2024-08-06",
      "price": 89.22
    },
    {
      "date": "2024-08-07",
      "price": 89.16
    },
    {
      "date": "2024-08-08",
      "price": 88.34
    },
    {
      "date": "2024-08-09",
      "price": 87.97
    },
    {
      "date": "2024-08-10",
      "price": 86.51
    },
    {
      "date": "2024-08-11",
      "price": 85.77
    },
    {
      "date": "2024-08-12",
      "price": 85.76
    },
    {
      "date": "2024-08-13",
      "price": 84.59
    },
    {
      "date": "2024-08-14",
      "price": 85.05
    },
    {
      "date": "2024-08-15",
      "price": 85.18
    },
    {
      "date": "2024-08-16",
      "price": 84.51
    },
    {
      "date": "2024-08-17",
      "price": 82.68
    },
    {
      "date": "2024-08-18",
      "price": 83.88
    },
    {
      "date": "2024-08-19",
      "price": 82.76
    },
    {
      "date": "2024-08-20",
      "price": 81.82
    },
    {
      "date": "2024-08-21",
      "price": 81.17
    },
    {
      "date": "2024-08-22",
      "price": 81.48
    },
    {
      "date": "2024-08-23",
      "price": 82.03
    },
    {
      "date": "2024-08-24",
      "price": 80.89
    },
    {
      "date": "2024-08-25",
      "price": 79.85
    },
    {
      "date": "2024-08-26",
      "price": 80.27
    },
    {
      "date": "2024-08-27",
      "price": 78.27
    },
    {
      "date": "2024-08-28",
      "price": 77.87
    },
    {
      "date": "2024-08-29",
      "price": 77.65
    },
    {
      "date": "2024-08-30",
      "price": 76.46
    },
    {
      "date": "2024-08-31",
      "price": 77.91
    },
    {
      "date": "2024-09-01",
      "price": 78.37
    },
    {
      "date": "2024-09-02",
      "price": 77.72
    },
    {
      "date": "2024-09-03",
      "price": 79.09
    },
    {
      "date": "2024-09-04",
      "price": 77.96
    },
    {
      "date": "2024-09-05",
      "price": 77.96
    },
    {
      "date": "2024-09-06",
      "price": 76.17
    },
    {
      "date": "2024-09-07",
      "price": 76.49
    },
    {
      "date": "2024-09-08",
      "price": 76.73
    },
    {
      "date": "2024-09-09",
      "price": 75.45
    },
    {
      "date": "2024-09-10",
      "price": 75.09
    },
    {
      "date": "2024-09-11",
      "price": 75.15
    },
    {
      "date": "2024-09-12",
      "price": 74.7
    },
    {
      "date": "2024-09-13",
      "price": 75.89
    },
    {
      "date": "2024-09-14",
      "price": 75.45
    },
    {
      "date": "2024-09-15",
      "price": 75.76
    },
    {
      "date": "2024-09-16",
      "price": 76.07
    },
    {
      "date": "2024-09-17",
      "price": 76.05
    },
    {
      "date": "2024-09-18",
      "price": 77.97
    },
    {
      "date": "2024-09-19",
      "price": 77.53
    },
    {
      "date": "2024-09-20",
      "price": 76.46
    },
    {
      "date": "2024-09-21",
      "price": 75.4
    },
    {
      "date": "2024-09-22",
      "price": 76.02
    },
    {
      "date": "2024-09-23",
      "price": 76.26
    },
    {
      "date": "2024-09-24",
      "price": 75.46
    },
    {
      "date": "2024-09-25",
      "price": 76.35
    },
    {
      "date": "2024-09-26",
      "price": 77.07
    },
    {
      "date": "2024-09-27",
      "price": 78.31
    },
    {
      "date": "2024-09-28",
      "price": 78.31
    },
    {
      "date": "2024-09-29",
      "price": 78.19
    },
    {
      "date": "2024-09-30",
      "price": 79.13
    },
    {
      "date": "2024-10-01",
      "price": 80.34
    },
    {
      "date": "2024-10-02",
      "price": 80.43
    },
    {
      "date": "2024-10-03",
      "price": 82.18
    },
    {
      "date": "2024-10-04",
      "price": 81.9
    },
    {
      "date": "2024-10-05",
      "price": 83.1
    },
    {
      "date": "2024-10-06",
      "price": 83.8
    },
    {
      "date": "2024-10-07",
      "price": 84.79
    },
    {
      "date": "2024-10-08",
      "price": 85.02
    },
    {
      "date": "2024-10-09",
      "price": 86.1
    },
    {
      "date": "2024-10-10",
      "price": 85.4
    },
    {
      "date": "2024-10-11",
      "price": 84.98
    },
    {
      "date": "2024-10-12",
      "price": 84.86
    },
    {
      "date": "2024-10-13",
      "price": 84.1
    },
    {
      "date": "2024-10-14",
      "price": 85.53
    },
    {
      "date": "2024-10-15",
      "price": 84.3
    },
    {
      "date": "2024-10-16",
      "price": 85.21
    },
    {
      "date": "2024-10-17",
      "price": 85.57
    },
    {
      "date": "2024-10-18",
      "price": 85.71
    },
    {
      "date": "2024-10-19",
      "price": 86.1
    },
    {
      "date": "2024-10-20",
      "price": 85.45
    },
    {
      "date": "2024-10-21",
      "price": 86.32
    },
    {
      "date": "2024-10-22",
      "price": 86.63
    },
    {
      "date": "2024-10-23",
      "price": 88.44
    },
    {
      "date": "2024-10-24",
      "price": 88.41
    },
    {
      "date": "2024-10-25",
      "price": 88.54
    },
    {
      "date": "2024-10-26",
      "price": 89.4
    },
    {
      "date": "2024-10-27",
      "price": 88.77
    },
    {
      "date": "2024-10-28",
      "price": 89.48
    },
    {
      "date": "2024-10-29",
      "price": 88.31
    },
    {
      "date": "2024-10-30",
      "price": 88.37
    },
    {
      "date": "2024-10-31",
      "price": 88.21
    },
    {
      "date": "2024-11-01",
      "price": 86.74
    },
    {
      "date": "2024-11-02",
      "price": 85.78
    },
    {
      "date": "2024-11-03",
      "price": 84.1
    },
    {
      "date": "2024-11-04",
      "price": 83.76
    },
    {
      "date": "2024-11-05",
      "price": 82.99
    },
    {
      "date": "2024-11-06",
      "price": 81.58
    },
    {
      "date": "2024-11-07",
      "price": 81.49
    },
    {
      "date": "2024-11-08",
      "price": 81.0
    },
    {
      "date": "2024-11-09",
      "price": 80.25
    },
    {
      "date": "2024-11-10",
      "price": 79.36
    },
    {
      "date": "2024-11-11",
      "price": 79.62
    },
    {
      "date": "2024-11-12",
      "price": 79.56
    },
    {
      "date": "2024-11-13",
      "price": 79.62
    },
    {
      "date": "2024-11-14",
      "price": 80.51
    },
    {
      "date": "2024-11-15",
      "price": 81.37
    },
    {
      "date": "2024-11-16",
      "price": 81.51
    },
    {
      "date": "2024-11-17",
      "price": 83.72
    },
    {
      "date": "2024-11-18",
      "price": 83.24
    },
    {
      "date": "2024-11-19",
      "price": 82.32
    },
    {
      "date": "2024-11-20",
      "price": 81.99
    },
    {
      "date": "2024-11-21",
      "price": 83.27
    },
    {
      "date": "2024-11-22",
      "price": 81.75
    },
    {
      "date": "2024-11-23",
      "price": 81.07
    },
    {
      "date": "2024-11-24",
      "price": 81.84
    },
    {
      "date": "2024-11-25",
      "price": 81.71
    },
    {
      "date": "2024-11-26",
      "price": 79.29
    },
    {
      "date": "2024-11-27",
      "price": 78.24
    },
    {
      "date": "2024-11-28",
      "price": 80.03
    },
    {
      "date": "2024-11-29",
      "price": 78.71
    },
    {
      "date": "2024-11-30",
      "price": 79.2
    },
    {
      "date": "2024-12-01",
      "price": 78.62
    },
    {
      "date": "2024-12-02",
      "price": 77.82
    },
    {
      "date": "2024-12-03",
      "price": 77.3
    },
    {
      "date": "2024-12-04",
      "price": 78.06
    },
    {
      "date": "2024-12-05",
      "price": 78.33
    },
    {
      "date": "2024-12-06",
      "price": 79.36
    },
    {
      "date": "2024-12-07",
      "price": 79.74
    },
    {
      "date": "2024-12-08",
      "price": 80.51
    },
    {
      "date": "2024-12-09",
      "price": 81.33
    },
    {
      "date": "2024-12-10",
      "price": 80.31
    },
    {
      "date": "2024-12-11",
      "price": 78.83
    },
    {
      "date": "2024-12-12",
      "price": 79.45
    },
    {
      "date": "2024-12-13",
      "price": 78.73
    },
    {
      "date": "2024-12-14",
      "price": 78.41
    },
    {
      "date": "2024-12-15",
      "price": 76.39
    },
    {
      "date": "2024-12-16",
      "price": 77.82
    },
    {
      "date": "2024-12-17",
      "price": 77.62
    },
    {
      "date": "2024-12-18",
      "price": 76.71
    },
    {
      "date": "2024-12-19",
      "price": 75.45
    },
    {
      "date": "2024-12-20",
      "price": 75.56
    },
    {
      "date": "2024-12-21",
      "price": 76.35
    },
    {
      "date": "2024-12-22",
      "price": 76.24
    },
    {
      "date": "2024-12-23",
      "price": 76.23
    },
    {
      "date": "2024-12-24",
      "price": 76.5
    },
    {
      "date": "2024-12-25",
      "price": 77.33
    },
    {
      "date": "2024-12-26",
      "price": 78.15
    },
    {
      "date": "2024-12-27",
      "price": 78.55
    },
    {
      "date": "2024-12-28",
      "price": 78.56
    },
    {
      "date": "2024-12-29",
      "price": 79.26
    },
    {
      "date": "2024-12-30",
      "price": 79.08
    },
    {
      "date": "2024-12-31",
      "price": 79.08
    },
    {
      "date": "2025-01-01",
      "price": 77.55
    },
    {
      "date": "2025-01-02",
      "price": 77.15
    },
    {
      "date": "2025-01-03",
      "price": 76.82
    },
    {
      "date": "2025-01-04",
      "price": 78.46
    },
    {
      "date": "2025-01-05",
      "price": 78.71
    },
    {
      "date": "2025-01-06",
      "price": 77.78
    },
    {
      "date": "2025-01-07",
      "price": 77.36
    },
    {
      "date": "2025-01-08",
      "price": 77.49
    },
    {
      "date": "2025-01-09",
      "price": 76.77
    },
    {
      "date": "2025-01-10",
      "price": 75.37
    },
    {
      "date": "2025-01-11",
      "price": 76.26
    },
    {
      "date": "2025-01-12",
      "price": 74.73
    },
    {
      "date": "2025-01-13",
      "price": 74.05
    },
    {
      "date": "2025-01-14",
      "price": 74.92
    },
    {
      "date": "2025-01-15",
      "price": 76.48
    },
    {
      "date": "2025-01-16",
      "price": 74.68
    },
    {
      "date": "2025-01-17",
      "price": 74.45
    },
    {
      "date": "2025-01-18",
      "price": 73.66
    },
    {
      "date": "2025-01-19",
      "price": 72.84
    },
    {
      "date": "2025-01-20",
      "price": 74.45
    },
    {
      "date": "2025-01-21",
      "price": 73.75
    },
    {
      "date": "2025-01-22",
      "price": 73.22
    },
    {
      "date": "2025-01-23",
      "price": 72.46
    },
    {
      "date": "2025-01-24",
      "price": 74.03
    },
    {
      "date": "2025-01-25",
      "price": 74.84
    },
    {
      "date": "2025-01-26",
      "price": 76.02
    },
    {
      "date": "2025-01-27",
      "price": 76.15
    },
    {
      "date": "2025-01-28",
      "price": 74.92
    },
    {
      "date": "2025-01-29",
      "price": 75.9
    },
    {
      "date": "2025-01-30",
      "price": 74.95
    },
    {
      "date": "2025-01-31",
      "price": 74.11
    },
    {
      "date": "2025-02-01",
      "price": 74.76
    },
    {
      "date": "2025-02-02",
      "price": 74.09
    },
    {
      "date": "2025-02-03",
      "price": 73.98
    },
    {
      "date": "2025-02-04",
      "price": 75.35
    },
    {
      "date": "2025-02-05",
      "price": 75.29
    },
    {
      "date": "2025-02-06",
      "price": 74.24
    },
    {
      "date": "2025-02-07",
      "price": 76.4
    },
    {
      "date": "2025-02-08",
      "price": 74.98
    },
    {
      "date": "2025-02-09",
      "price": 75.83
    },
    {
      "date": "2025-02-10",
      "price": 76.78
    },
    {
      "date": "2025-02-11",
      "price": 76.2
    },
    {
      "date": "2025-02-12",
      "price": 74.85
    },
    {
      "date": "2025-02-13",
      "price": 74.38
    },
    {
      "date": "2025-02-14",
      "price": 74.8
    },
    {
      "date": "2025-02-15",
      "price": 74.57
    },
    {
      "date": "2025-02-16",
      "price": 75.19
    },
    {
      "date": "2025-02-17",
      "price": 75.86
    },
    {
      "date": "2025-02-18",
      "price": 76.39
    },
    {
      "date": "2025-02-19",
      "price": 77.59
    },
    {
      "date": "2025-02-20",
      "price": 76.51
    },
    {
      "date": "2025-02-21",
      "price": 75.0
    },
    {
      "date": "2025-02-22",
      "price": 75.7
    },
    {
      "date": "2025-02-23",
      "price": 76.67
    },
    {
      "date": "2025-02-24",
      "price": 76.68
    },
    {
      "date": "2025-02-25",
      "price": 75.84
    },
    {
      "date": "2025-02-26",
      "price": 74.83
    },
    {
      "date": "2025-02-27",
      "price": 74.87
    },
    {
      "date": "2025-02-28",
      "price": 73.66
    },
    {
      "date": "2025-03-01",
      "price": 72.64
    },
    {
      "date": "2025-03-02",
      "price": 73.01
    },
    {
      "date": "2025-03-03",
      "price": 72.74
    },
    {
      "date": "2025-03-04",
      "price": 72.83
    },
    {
      "date": "2025-03-05",
      "price": 71.3
    },
    {
      "date": "2025-03-06",
      "price": 71.22
    },
    {
      "date": "2025-03-07",
      "price": 69.76
    },
    {
      "date": "2025-03-08",
      "price": 68.22
    },
    {
      "date": "2025-03-09",
      "price": 66.11
    },
    {
      "date": "2025-03-10",
      "price": 68.08
    },
    {
      "date": "2025-03-11",
      "price": 67.16
    },
    {
      "date": "2025-03-12",
      "price": 65.93
    },
    {
      "date": "2025-03-13",
      "price": 65.49
    },
    {
      "date": "2025-03-14",
      "price": 65.29
    },
    {
      "date": "2025-03-15",
      "price": 65.06
    },
    {
      "date": "2025-03-16",
      "price": 65.17
    },
    {
      "date": "2025-03-17",
      "price": 63.98
    },
    {
      "date": "2025-03-18",
      "price": 65.74
    },
    {
      "date": "2025-03-19",
      "price": 64.99
    },
    {
      "date": "2025-03-20",
      "price": 64.48
    },
    {
      "date": "2025-03-21",
      "price": 64.03
    },
    {
      "date": "2025-03-22",
      "price": 64.99
    },
    {
      "date": "2025-03-23",
      "price": 65.39
    },
    {
      "date": "2025-03-24",
      "price": 64.93
    },
    {
      "date": "2025-03-25",
      "price": 65.51
    },
    {
      "date": "2025-03-26",
      "price": 65.43
    },
    {
      "date": "2025-03-27",
      "price": 66.03
    },
    {
      "date": "2025-03-28",
      "price": 64.71
    },
    {
      "date": "2025-03-29",
      "price": 64.77
    },
    {
      "date": "2025-03-30",
      "price": 65.4
    },
    {
      "date": "2025-03-31",
      "price": 66.23
    },
    {
      "date": "2025-04-01",
      "price": 64.76
    },
    {
      "date": "2025-04-02",
      "price": 65.63
    },
    {
      "date": "2025-04-03",
      "price": 66.04
    },
    {
      "date": "2025-04-04",
      "price": 65.42
    },
    {
      "date": "2025-04-05",
      "price": 65.26
    },
    {
      "date": "2025-04-06",
      "price": 66.49
    },
    {
      "date": "2025-04-07",
      "price": 67.31
    },
    {
      "date": "2025-04-08",
      "price": 68.49
    },
    {
      "date": "2025-04-09",
      "price": 69.77
    },
    {
      "date": "2025-04-10",
      "price": 70.17
    },
    {
      "date": "2025-04-11",
      "price": 69.85
    },
    {
      "date": "2025-04-12",
      "price": 69.99
    },
    {
      "date": "2025-04-13",
      "price": 69.54
    },
    {
      "date": "2025-04-14",
      "price": 69.3
    },
    {
      "date": "2025-04-15",
      "price": 69.15
    },
    {
      "date": "2025-04-16",
      "price": 67.93
    },
    {
      "date": "2025-04-17",
      "price": 68.3
    },
    {
      "date": "2025-04-18",
      "price": 67.49
    },
    {
      "date": "2025-04-19",
      "price": 68.37
    },
    {
      "date": "2025-04-20",
      "price": 68.87
    },
    {
      "date": "2025-04-21",
      "price": 68.63
    },
    {
      "date": "2025-04-22",
      "price": 68.36
    },
    {
      "date": "2025-04-23",
      "price": 67.75
    },
    {
      "date": "2025-04-24",
      "price": 69.09
    },
    {
      "date": "2025-04-25",
      "price": 70.09
    },
    {
      "date": "2025-04-26",
      "price": 71.49
    },
    {
      "date": "2025-04-27",
      "price": 70.9
    },
    {
      "date": "2025-04-28",
      "price": 68.55
    },
    {
      "date": "2025-04-29",
      "price": 68.9
    },
    {
      "date": "2025-04-30",
      "price": 67.93
    },
    {
      "date": "2025-05-01",
      "price": 68.72
    },
    {
      "date": "2025-05-02",
      "price": 68.86
    },
    {
      "date": "2025-05-03",
      "price": 69.29
    },
    {
      "date": "2025-05-04",
      "price": 68.75
    },
    {
      "date": "2025-05-05",
      "price": 69.41
    },
    {
      "date": "2025-05-06",
      "price": 69.37
    },
    {
      "date": "2025-05-07",
      "price": 69.33
    },
    {
      "date": "2025-05-08",
      "price": 69.77
    },
    {
      "date": "2025-05-09",
      "price": 67.74
    },
    {
      "date": "2025-05-10",
      "price": 66.98
    },
    {
      "date": "2025-05-11",
      "price": 69.24
    },
    {
      "date": "2025-05-12",
      "price": 67.98
    },
    {
      "date": "2025-05-13",
      "price": 69.13
    },
    {
      "date": "2025-05-14",
      "price": 68.51
    },
    {
      "date": "2025-05-15",
      "price": 68.28
    },
    {
      "date": "2025-05-16",
      "price": 66.71
    },
    {
      "date": "2025-05-17",
      "price": 68.25
    },
    {
      "date": "2025-05-18",
      "price": 68.1
    },
    {
      "date": "2025-05-19",
      "price": 68.24
    },
    {
      "date": "2025-05-20",
      "price": 68.16
    },
    {
      "date": "2025-05-21",
      "price": 68.05
    },
    {
      "date": "2025-05-22",
      "price": 67.0
    },
    {
      "date": "2025-05-23",
      "price": 67.27
    },
    {
      "date": "2025-05-24",
      "price": 66.85
    },
    {
      "date": "2025-05-25",
      "price": 65.34
    },
    {
      "date": "2025-05-26",
      "price": 64.45
    },
    {
      "date": "2025-05-27",
      "price": 65.1
    },
    {
      "date": "2025-05-28",
      "price": 63.67
    },
    {
      "date": "2025-05-29",
      "price": 64.94
    },
    {
      "date": "2025-05-30",
      "price": 64.04
    },
    {
      "date": "2025-05-31",
      "price": 63.89
    },
    {
      "date": "2025-06-01",
      "price": 62.96
    },
    {
      "date": "2025-06-02",
      "price": 63.61
    },
    {
      "date": "2025-06-03",
      "price": 64.51
    },
    {
      "date": "2025-06-04",
      "price": 63.91
    },
    {
      "date": "2025-06-05",
      "price": 64.44
    },
    {
      "date": "2025-06-06",
      "price": 64.25
    },
    {
      "date": "2025-06-07",
      "price": 63.68
    },
    {
      "date": "2025-06-08",
      "price": 61.92
    },
    {
      "date": "2025-06-09",
      "price": 60.63
    },
    {
      "date": "2025-06-10",
      "price": 61.8
    },
    {
      "date": "2025-06-11",
      "price": 61.88
    },
    {
      "date": "2025-06-12",
      "price": 63.45
    },
    {
      "date": "2025-06-13",
      "price": 61.64
    },
    {
      "date": "2025-06-14",
      "price": 62.27
    },
    {
      "date": "2025-06-15",
      "price": 63.29
    },
    {
      "date": "2025-06-16",
      "price": 61.79
    },
    {
      "date": "2025-06-17",
      "price": 62.43
    },
    {
      "date": "2025-06-18",
      "price": 62.59
    },
    {
      "date": "2025-06-19",
      "price": 61.6
    },
    {
      "date": "2025-06-20",
      "price": 61.69
    }
  ],
  "intrinsicValueEstimates": [
    {
      "period": "Q1",
      "startDate": "2024-01-01",
      "endDate": "2024-03-31",
      "min": 75.71,
      "max": 79.72
    },
    {
      "period": "Q2",
      "startDate": "2024-04-01",
      "endDate": "2024-06-30",
      "min": 73.48,
      "max": 76.96
    },
    {
      "period": "Q3",
      "startDate": "2024-07-01",
      "endDate": "2024-09-30",
      "min": 74.66,
      "max": 77.59
    },
    {
      "period": "Q4",
      "startDate": "2024-10-01",
      "endDate": "2024-12-31",
      "min": 73.7,
      "max": 78.9
    }
  ],
  "evaluationMetrics": {
    "PE": [
      {
        "year": 2022,
        "value": 6.178,
        "label": "good"
      },
      {
        "year": 2023,
        "value": 24.491,
        "label": "neutral"
      },
      {
        "year": 2024,
        "value": 32.988,
        "label": "bad"
      }
    ],
    "ROE": [
      {
        "year": 2022,
        "value": 0.116,
        "label": "neutral"
      },
      {
        "year": 2023,
        "value": 0.095,
        "label": "neutral"
      },
      {
        "year": 2024,
        "value": 0.129,
        "label": "neutral"
      }
    ],
    "DebtEquity": [
      {
        "year": 2022,
        "value": 1.873,
        "label": "neutral"
      },
      {
        "year": 2023,
        "value": 2.504,
        "label": "bad"
      },
      {
        "year": 2024,
        "value": 2.45,
        "label": "bad"
      }
    ],
    "CurrentRatio": [
      {
        "year": 2022,
        "value": 2.682,
        "label": "good"
      },
      {
        "year": 2023,
        "value": 1.42,
        "label": "neutral"
      },
      {
        "year": 2024,
        "value": 1.466,
        "label": "neutral"
      }
    ],
    "Margin": [
      {
        "year": 2022,
        "value": 0.054,
        "label": "bad"
      },
      {
        "year": 2023,
        "value": 0.09,
        "label": "bad"
      },
      {
        "year": 2024,
        "value": 0.294,
        "label": "good"
      }
    ],
    "Beta": [
      {
        "year": 2022,
        "value": 1.433,
        "label": "bad"
      },
      {
        "year": 2023,
        "value": 0.779,
        "label": "good"
      },
      {
        "year": 2024,
        "value": 1.244,
        "label": "neutral"
      }
    ],
    "PBV": [
      {
        "year": 2022,
        "value": 6.773,
        "label": "bad"
      },
      {
        "year": 2023,
        "value": 1.935,
        "label": "good"
      },
      {
        "year": 2024,
        "value": 1.029,
        "label": "good"
      }
    ],
    "DividendYield": [
      {
        "year": 2022,
        "value": 0.052,
        "label": "good"
      },
      {
        "year": 2023,
        "value": 0.014,
        "label": "neutral"
      },
      {
        "year": 2024,
        "value": 0.005,
        "label": "bad"
      }
    ]
  }
}