{
  "companyName": "Galvan Inc",
  "description": "Significant but various. Court north military he capital. Item around else line want.\nWide hundred all. Yeah significant street cup.\nSometimes expert serve trouble test school.\nSeven few other spring. Point oil ask event could easy development.",
  "dailyStockPrice": [
    {
      "date": "2024-06-23",
      "price": 458.09
    },
    {
      "date": "2024-06-24",
      "price": 457.66
    },
    {
      "date": "2024-06-25",
      "price": 457.44
    },
    {
      "date": "2024-06-26",
      "price": 456.14
    },
    {
      "date": "2024-06-27",
      "price": 456.23
    },
    {
      "date": "2024-06-28",
      "price": 454.69
    },
    {
      "date": "2024-06-29",
      "price": 454.31
    },
    {
      "date": "2024-06-30",
      "price": 454.13
    },
    {
      "date": "2024-07-01",
      "price": 454.95
    },
    {
      "date": "2024-07-02",
      "price": 455.59
    },
    {
      "date": "2024-07-03",
      "price": 456.14
    },
    {
      "date": "2024-07-04",
      "price": 458.08
    },
    {
      "date": "2024-07-05",
      "price": 456.52
    },
    {
      "date": "2024-07-06",
      "price": 455.82
    },
    {
      "date": "2024-07-07",
      "price": 456.36
    },
    {
      "date": "2024-07-08",
      "price": 455.92
    },
    {
      "date": "2024-07-09",
      "price": 455.6
    },
    {
      "date": "2024-07-10",
      "price": 453.95
    },
    {
      "date": "2024-07-11",
      "price": 453.61
    },
    {
      "date": "2024-07-12",
      "price": 454.27
    },
    {
      "date": "2024-07-13",
      "price": 454.07
    },
    {
      "date": "2024-07-14",
      "price": 452.95
    },
    {
      "date": "2024-07-15",
      "price": 451.95
    },
    {
      "date": "2024-07-16",
      "price": 452.05
    },
    {
      "date": "2024-07-17",
      "price": 451.4
    },
    {
      "date": "2024-07-18",
      "price": 450.36
    },
    {
      "date": "2024-07-19",
      "price": 451.95
    },
    {
      "date": "2024-07-20",
      "price": 452.53
    },
    {
      "date": "2024-07-21",
      "price": 452.1
    },
    {
      "date": "2024-07-22",
      "price": 452.5
    },
    {
      "date": "2024-07-23",
      "price": 453.42
    },
    {
      "date": "2024-07-24",
      "price": 453.9
    },
    {
      "date": "2024-07-25",
      "price": 454.68
    },
    {
      "date": "2024-07-26",
      "price": 453.68
    },
    {
      "date": "2024-07-27",
      "price": 452.94
    },
    {
      "date": "2024-07-28",
      "price": 452.14
    },
    {
      "date": "2024-07-29",
      "price": 450.87
    },
    {
      "date": "2024-07-30",
      "price": 450.95
    },
    {
      "date": "2024-07-31",
      "price": 452.1
    },
    {
      "date": "2024-08-01",
      "price": 450.9
    },
    {
      "date": "2024-08-02",
      "price": 449.81
    },
    {
      "date": "2024-08-03",
      "price": 448.64
    },
    {
      "date": "2024-08-04",
      "price": 448.9
    },
    {
      "date": "2024-08-05",
      "price": 449.8
    },
    {
      "date": "2024-08-06",
      "price": 448.01
    },
    {
      "date": "2024-08-07",
      "price": 449.63
    },
    {
      "date": "2024-08-08",
      "price": 450.44
    },
    {
      "date": "2024-08-09",
      "price": 449.4
    },
    {
      "date": "2024-08-10",
      "price": 449.44
    },
    {
      "date": "2024-08-11",
      "price": 449.88
    },
    {
      "date": "2024-08-12",
      "price": 450.65
    },
    {
      "date": "2024-08-13",
      "price": 448.94
    },
    {
      "date": "2024-08-14",
      "price": 448.27
    },
    {
      "date": "2024-08-15",
      "price": 448.52
    },
    {
      "date": "2024-08-16",
      "price": 449.84
    },
    {
      "date": "2024-08-17",
      "price": 450.53
    },
    {
      "date": "2024-08-18",
      "price": 450.2
    },
    {
      "date": "2024-08-19",
      "price": 450.12
    },
    {
      "date": "2024-08-20",
      "price": 448.06
    },
    {
      "date": "2024-08-21",
      "price": 448.29
    },
    {
      "date": "2024-08-22",
      "price": 449.16
    },
    {
      "date": "2024-08-23",
      "price": 449.2
    },
    {
      "date": "2024-08-24",
      "price": 447.48
    },
    {
      "date": "2024-08-25",
      "price": 446.72
    },
    {
      "date": "2024-08-26",
      "price": 447.06
    },
    {
      "date": "2024-08-27",
      "price": 446.53
    },
    {
      "date": "2024-08-28",
      "price": 445.11
    },
    {
      "date": "2024-08-29",
      "price": 444.74
    },
    {
      "date": "2024-08-30",
      "price": 445.25
    },
    {
      "date": "2024-08-31",
      "price": 445.43
    },
    {
      "date": "2024-09-01",
      "price": 446.18
    },
    {
      "date": "2024-09-02",
      "price": 447.03
    },
    {
      "date": "2024-09-03",
      "price": 446.12
    },
    {
      "date": "2024-09-04",
      "price": 446.96
    },
    {
      "date": "2024-09-05",
      "price": 448.62
    },
    {
      "date": "2024-09-06",
      "price": 447.92
    },
    {
      "date": "2024-09-07",
      "price": 447.14
    },
    {
      "date": "2024-09-08",
      "price": 446.37
    },
    {
      "date": "2024-09-09",
      "price": 447.69
    },
    {
      "date": "2024-09-10",
      "price": 448.29
    },
    {
      "date": "2024-09-11",
      "price": 448.78
    },
    {
      "date": "2024-09-12",
      "price": 450.29
    },
    {
      "date": "2024-09-13",
      "price": 450.16
    },
    {
      "date": "2024-09-14",
      "price": 448.69
    },
    {
      "date": "2024-09-15",
      "price": 449.09
    },
    {
      "date": "2024-09-16",
      "price": 447.01
    },
    {
      "date": "2024-09-17",
      "price": 448.31
    },
    {
      "date": "2024-09-18",
      "price": 448.23
    },
    {
      "date": "2024-09-19",
      "price": 448.87
    },
    {
      "date": "2024-09-20",
      "price": 449.66
    },
    {
      "date": "2024-09-21",
      "price": 451.37
    },
    {
      "date": "2024-09-22",
      "price": 451.72
    },
    {
      "date": "2024-09-23",
      "price": 452.5
    },
    {
      "date": "2024-09-24",
      "price": 452.82
    },
    {
      "date": "2024-09-25",
      "price": 451.94
    },
    {
      "date": "2024-09-26",
      "price": 451.63
    },
    {
      "date": "2024-09-27",
      "price": 452.28
    },
    {
      "date": "2024-09-28",
      "price": 452.63
    },
    {
      "date": "2024-09-29",
      "price": 452.66
    },
    {
      "date": "2024-09-30",
      "price": 453.66
    },
    {
      "date": "2024-10-01",
      "price": 454.96
    },
    {
      "date": "2024-10-02",
      "price": 454.36
    },
    {
      "date": "2024-10-03",
      "price": 452.82
    },
    {
      "date": "2024-10-04",
      "price": 451.73
    },
    {
      "date": "2024-10-05",
      "price": 451.94
    },
    {
      "date": "2024-10-06",
      "price": 450.77
    },
    {
      "date": "2024-10-07",
      "price": 451.55
    },
    {
      "date": "2024-10-08",
      "price": 451.48
    },
    {
      "date": "2024-10-09",
      "price": 452.7
    },
    {
      "date": "2024-10-10",
      "price": 451.87
    },
    {
      "date": "2024-10-11",
      "price": 450.66
    },
    {
      "date": "2024-10-12",
      "price": 449.64
    },
    {
      "date": "2024-10-13",
      "price": 448.17
    },
    {
      "date": "2024-10-14",
      "price": 449.68
    },
    {
      "date": "2024-10-15",
      "price": 449.66
    },
    {
      "date": "2024-10-16",
      "price": 449.16
    },
    {
      "date": "2024-10-17",
      "price": 448.3
    },
    {
      "date": "2024-10-18",
      "price": 448.08
    },
    {
      "date": "2024-10-19",
      "price": 447.57
    },
    {
      "date": "2024-10-20",
      "price": 448.99
    },
    {
      "date": "2024-10-21",
      "price": 449.39
    },
    {
      "date": "2024-10-22",
      "price": 449.04
    },
    {
      "date": "2024-10-23",
      "price": 450.62
    },
    {
      "date": "2024-10-24",
      "price": 450.83
    },
    {
      "date": "2024-10-25",
      "price": 451.09
    },
    {
      "date": "2024-10-26",
      "price": 451.82
    },
    {
      "date": "2024-10-27",
      "price": 452.89
    },
    {
      "date": "2024-10-28",
      "price": 452.58
    },
    {
      "date": "2024-10-29",
      "price": 451.63
    },
    {
      "date": "2024-10-30",
      "price": 452.82
    },
    {
      "date": "2024-10-31",
      "price": 453.97
    },
    {
      "date": "2024-11-01",
      "price": 453.3
    },
    {
      "date": "2024-11-02",
      "price": 452.52
    },
    {
      "date": "2024-11-03",
      "price": 451.13
    },
    {
      "date": "2024-11-04",
      "price": 449.45
    },
    {
      "date": "2024-11-05",
      "price": 450.81
    },
    {
      "date": "2024-11-06",
      "price": 452.04
    },
    {
      "date": "2024-11-07",
      "price": 451.22
    },
    {
      "date": "2024-11-08",
      "price": 451.61
    },
    {
      "date": "2024-11-09",
      "price": 451.27
    },
    {
      "date": "2024-11-10",
      "price": 451.74
    },
    {
      "date": "2024-11-11",
      "price": 450.48
    },
    {
      "date": "2024-11-12",
      "price": 450.67
    },
    {
      "date": "2024-11-13",
      "price": 451.53
    },
    {
      "date": "2024-11-14",
      "price": 450.3
    },
    {
      "date": "2024-11-15",
      "price": 450.14
    },
    {
      "date": "2024-11-16",
      "price": 451.38
    },
    {
      "date": "2024-11-17",
      "price": 452.25
    },
    {
      "date": "2024-11-18",
      "price": 452.12
    },
    {
      "date": "2024-11-19",
      "price": 453.35
    },
    {
      "date": "2024-11-20",
      "price": 453.77
    },
    {
      "date": "2024-11-21",
      "price": 453.66
    },
    {
      "date": "2024-11-22",
      "price": 452.28
    },
    {
      "date": "2024-11-23",
      "price": 452.17
    },
    {
      "date": "2024-11-24",
      "price": 452.0
    },
    {
      "date": "2024-11-25",
      "price": 451.26
    },
    {
      "date": "2024-11-26",
      "price": 451.64
    },
    {
      "date": "2024-11-27",
      "price": 452.62
    },
    {
      "date": "2024-11-28",
      "price": 451.83
    },
    {
      "date": "2024-11-29",
      "price": 451.45
    },
    {
      "date": "2024-11-30",
      "price": 452.58
    },
    {
      "date": "2024-12-01",
      "price": 452.6
    },
    {
      "date": "2024-12-02",
      "price": 454.61
    },
    {
      "date": "2024-12-03",
      "price": 454.86
    },
    {
      "date": "2024-12-04",
      "price": 456.38
    },
    {
      "date": "2024-12-05",
      "price": 457.61
    },
    {
      "date": "2024-12-06",
      "price": 456.44
    },
    {
      "date": "2024-12-07",
      "price": 457.64
    },
    {
      "date": "2024-12-08",
      "price": 458.36
    },
    {
      "date": "2024-12-09",
      "price": 456.72
    },
    {
      "date": "2024-12-10",
      "price": 456.23
    },
    {
      "date": "2024-12-11",
      "price": 455.95
    },
    {
      "date": "2024-12-12",
      "price": 456.55
    },
    {
      "date": "2024-12-13",
      "price": 456.25
    },
    {
      "date": "2024-12-14",
      "price": 457.31
    },
    {
      "date": "2024-12-15",
      "price": 459.08
    },
    {
      "date": "2024-12-16",
      "price": 459.71
    },
    {
      "date": "2024-12-17",
      "price": 458.84
    },
    {
      "date": "2024-12-18",
      "price": 458.43
    },
    {
      "date": "2024-12-19",
      "price": 458.59
    },
    {
      "date": "2024-12-20",
      "price": 458.45
    },
    {
      "date": "2024-12-21",
      "price": 457.5
    },
    {
      "date": "2024-12-22",
      "price": 457.18
    },
    {
      "date": "2024-12-23",
      "price": 456.52
    },
    {
      "date": "2024-12-24",
      "price": 458.25
    },
    {
      "date": "2024-12-25",
      "price": 457.61
    },
    {
      "date": "2024-12-26",
      "price": 456.81
    },
    {
      "date": "2024-12-27",
      "price": 458.01
    },
    {
      "date": "2024-12-28",
      "price": 456.93
    },
    {
      "date": "2024-12-29",
      "price": 456.89
    },
    {
      "date": "2024-12-30",
      "price": 455.93
    },
    {
      "date": "2024-12-31",
      "price": 455.01
    },
    {
      "date": "2025-01-01",
      "price": 453.99
    },
    {
      "date": "2025-01-02",
      "price": 455.03
    },
    {
      "date": "2025-01-03",
      "price": 455.45
    },
    {
      "date": "2025-01-04",
      "price": 455.47
    },
    {
      "date": "2025-01-05",
      "price": 454.53
    },
    {
      "date": "2025-01-06",
      "price": 454.94
    },
    {
      "date": "2025-01-07",
      "price": 457.11
    },
    {
      "date": "2025-01-08",
      "price": 457.06
    },
    {
      "date": "2025-01-09",
      "price": 458.3
    },
    {
      "date": "2025-01-10",
      "price": 458.46
    },
    {
      "date": "2025-01-11",
      "price": 459.66
    },
    {
      "date": "2025-01-12",
      "price": 460.6
    },
    {
      "date": "2025-01-13",
      "price": 461.8
    },
    {
      "date": "2025-01-14",
      "price": 460.98
    },
    {
      "date": "2025-01-15",
      "price": 460.4
    },
    {
      "date": "2025-01-16",
      "price": 460.02
    },
    {
      "date": "2025-01-17",
      "price": 458.68
    },
    {
      "date": "2025-01-18",
      "price": 458.17
    },
    {
      "date": "2025-01-19",
      "price": 457.1
    },
    {
      "date": "2025-01-20",
      "price": 457.8
    },
    {
      "date": "2025-01-21",
      "price": 456.93
    },
    {
      "date": "2025-01-22",
      "price": 457.19
    },
    {
      "date": "2025-01-23",
      "price": 458.18
    },
    {
      "date": "2025-01-24",
      "price": 457.83
    },
    {
      "date": "2025-01-25",
      "price": 458.37
    },
    {
      "date": "2025-01-26",
      "price": 456.83
    },
    {
      "date": "2025-01-27",
      "price": 456.35
    },
    {
      "date": "2025-01-28",
      "price": 457.5
    },
    {
      "date": "2025-01-29",
      "price": 459.12
    },
    {
      "date": "2025-01-30",
      "price": 458.54
    },
    {
      "date": "2025-01-31",
      "price": 458.94
    },
    {
      "date": "2025-02-01",
      "price": 457.31
    },
    {
      "date": "2025-02-02",
      "price": 458.29
    },
    {
      "date": "2025-02-03",
      "price": 459.09
    },
    {
      "date": "2025-02-04",
      "price": 458.09
    },
    {
      "date": "2025-02-05",
      "price": 458.05
    },
    {
      "date": "2025-02-06",
      "price": 458.5
    },
    {
      "date": "2025-02-07",
      "price": 459.59
    },
    {
      "date": "2025-02-08",
      "price": 459.35
    },
    {
      "date": "2025-02-09",
      "price": 458.2
    },
    {
      "date": "2025-02-10",
      "price": 457.66
    },
    {
      "date": "2025-02-11",
      "price": 459.18
    },
    {
      "date": "2025-02-12",
      "price": 459.07
    },
    {
      "date": "2025-02-13",
      "price": 457.56
    },
    {
      "date": "2025-02-14",
      "price": 458.34
    },
    {
      "date": "2025-02-15",
      "price": 458.89
    },
    {
      "date": "2025-02-16",
      "price": 458.4
    },
    {
      "date": "2025-02-17",
      "price": 457.55
    },
    {
      "date": "2025-02-18",
      "price": 457.39
    },
    {
      "date": "2025-02-19",
      "price": 456.34
    },
    {
      "date": "2025-02-20",
      "price": 455.32
    },
    {
      "date": "2025-02-21",
      "price": 455.27
    },
    {
      "date": "2025-02-22",
      "price": 454.77
    },
    {
      "date": "2025-02-23",
      "price": 455.35
    },
    {
      "date": "2025-02-24",
      "price": 453.36
    },
    {
      "date": "2025-02-25",
      "price": 452.42
    },
    {
      "date": "2025-02-26",
      "price": 451.13
    },
    {
      "date": "2025-02-27",
      "price": 452.36
    },
    {
      "date": "2025-02-28",
      "price": 451.29
    },
    {
      "date": "2025-03-01",
      "price": 452.63
    },
    {
      "date": "2025-03-02",
      "price": 452.39
    },
    {
      "date": "2025-03-03",
      "price": 451.09
    },
    {
      "date": "2025-03-04",
      "price": 453.2
    },
    {
      "date": "2025-03-05",
      "price": 453.16
    },
    {
      "date": "2025-03-06",
      "price": 452.91
    },
    {
      "date": "2025-03-07",
      "price": 453.96
    },
    {
      "date": "2025-03-08",
      "price": 453.18
    },
    {
      "date": "2025-03-09",
      "price": 451.57
    },
    {
      "date": "2025-03-10",
      "price": 451.44
    },
    {
      "date": "2025-03-11",
      "price": 452.26
    },
    {
      "date": "2025-03-12",
      "price": 451.07
    },
    {
      "date": "2025-03-13",
      "price": 450.6
    },
    {
      "date": "2025-03-14",
      "price": 449.55
    },
    {
      "date": "2025-03-15",
      "price": 449.78
    },
    {
      "date": "2025-03-16",
      "price": 449.26
    },
    {
      "date": "2025-03-17",
      "price": 450.13
    },
    {
      "date": "2025-03-18",
      "price": 448.52
    },
    {
      "date": "2025-03-19",
      "price": 449.88
    },
    {
      "date": "2025-03-20",
      "price": 448.66
    },
    {
      "date": "2025-03-21",
      "price": 447.09
    },
    {
      "date": "2025-03-22",
      "price": 445.95
    },
    {
      "date": "2025-03-23",
      "price": 447.09
    },
    {
      "date": "2025-03-24",
      "price": 445.79
    },
    {
      "date": "2025-03-25",
      "price": 445.06
    },
    {
      "date": "2025-03-26",
      "price": 444.74
    },
    {
      "date": "2025-03-27",
      "price": 444.45
    },
    {
      "date": "2025-03-28",
      "price": 445.01
    },
    {
      "date": "2025-03-29",
      "price": 443.91
    },
    {
      "date": "2025-03-30",
      "price": 445.64
    },
    {
      "date": "2025-03-31",
      "price": 445.02
    },
    {
      "date": "2025-04-01",
      "price": 445.13
    },
    {
      "date": "2025-04-02",
      "price": 443.77
    },
    {
      "date": "2025-04-03",
      "price": 443.58
    },
    {
      "date": "2025-04-04",
      "price": 443.85
    },
    {
      "date": "2025-04-05",
      "price": 443.38
    },
    {
      "date": "2025-04-06",
      "price": 444.01
    },
    {
      "date": "2025-04-07",
      "price": 443.58
    },
    {
      "date": "2025-04-08",
      "price": 444.48
    },
    {
      "date": "2025-04-09",
      "price": 444.66
    },
    {
      "date": "2025-04-10",
      "price": 444.28
    },
    {
      "date": "2025-04-11",
      "price": 444.87
    },
    {
      "date": "2025-04-12",
      "price": 446.05
    },
    {
      "date": "2025-04-13",
      "price": 446.0
    },
    {
      "date": "2025-04-14",
      "price": 445.97
    },
    {
      "date": "2025-04-15",
      "price": 447.25
    },
    {
      "date": "2025-04-16",
      "price": 447.42
    },
    {
      "date": "2025-04-17",
      "price": 448.85
    },
    {
      "date": "2025-04-18",
      "price": 449.7
    },
    {
      "date": "2025-04-19",
      "price": 449.26
    },
    {
      "date": "2025-04-20",
      "price": 449.87
    },
    {
      "date": "2025-04-21",
      "price": 449.18
    },
    {
      "date": "2025-04-22",
      "price": 450.18
    },
    {
      "date": "2025-04-23",
      "price": 449.48
    },
    {
      "date": "2025-04-24",
      "price": 448.58
    },
    {
      "date": "2025-04-25",
      "price": 449.52
    },
    {
      "date": "2025-04-26",
      "price": 448.62
    },
    {
      "date": "2025-04-27",
      "price": 449.48
    },
    {
      "date": "2025-04-28",
      "price": 450.51
    },
    {
      "date": "2025-04-29",
      "price": 451.73
    },
    {
      "date": "2025-04-30",
      "price": 453.32
    },
    {
      "date": "2025-05-01",
      "price": 453.86
    },
    {
      "date": "2025-05-02",
      "price": 453.27
    },
    {
      "date": "2025-05-03",
      "price": 452.68
    },
    {
      "date": "2025-05-04",
      "price": 452.33
    },
    {
      "date": "2025-05-05",
      "price": 453.79
    },
    {
      "date": "2025-05-06",
      "price": 454.49
    },
    {
      "date": "2025-05-07",
      "price": 454.62
    },
    {
      "date": "2025-05-08",
      "price": 454.91
    },
    {
      "date": "2025-05-09",
      "price": 454.45
    },
    {
      "date": "2025-05-10",
      "price": 454.34
    },
    {
      "date": "2025-05-11",
      "price": 454.01
    },
    {
      "date": "2025-05-12",
      "price": 455.02
    },
    {
      "date": "2025-05-13",
      "price": 455.67
    },
    {
      "date": "2025-05-14",
      "price": 457.24
    },
    {
      "date": "2025-05-15",
      "price": 456.9
    },
    {
      "date": "2025-05-16",
      "price": 456.77
    },
    {
      "date": "2025-05-17",
      "price": 455.87
    },
    {
      "date": "2025-05-18",
      "price": 457.36
    },
    {
      "date": "2025-05-19",
      "price": 458.17
    },
    {
      "date": "2025-05-20",
      "price": 457.07
    },
    {
      "date": "2025-05-21",
      "price": 458.25
    },
    {
      "date": "2025-05-22",
      "price": 458.76
    },
    {
      "date": "2025-05-23",
      "price": 458.59
    },
    {
      "date": "2025-05-24",
      "price": 459.2
    },
    {
      "date": "2025-05-25",
      "price": 459.72
    },
    {
      "date": "2025-05-26",
      "price": 459.03
    },
    {
      "date": "2025-05-27",
      "price": 460.99
    },
    {
      "date": "2025-05-28",
      "price": 459.85
    },
    {
      "date": "2025-05-29",
      "price": 459.34
    },
    {
      "date": "2025-05-30",
      "price": 460.25
    },
    {
      "date": "2025-05-31",
      "price": 459.07
    },
    {
      "date": "2025-06-01",
      "price": 458.45
    },
    {
      "date": "2025-06-02",
      "price": 459.73
    },
    {
      "date": "2025-06-03",
      "price": 459.64
    },
    {
      "date": "2025-06-04",
      "price": 459.0
    },
    {
      "date": "2025-06-05",
      "price": 459.37
    },
    {
      "date": "2025-06-06",
      "price": 458.07
    },
    {
      "date": "2025-06-07",
      "price": 458.19
    },
    {
      "date": "2025-06-08",
      "price": 459.16
    },
    {
      "date": "2025-06-09",
      "price": 458.46
    },
    {
      "date": "2025-06-10",
      "price": 457.92
    },
    {
      "date": "2025-06-11",
      "price": 459.14
    },
    {
      "date": "2025-06-12",
      "price": 457.8
    },
    {
      "date": "2025-06-13",
      "price": 457.17
    },
    {
      "date": "2025-06-14",
      "price": 456.03
    },
    {
      "date": "2025-06-15",
      "price": 456.61
    },
    {
      "date": "2025-06-16",
      "price": 456.64
    },
    {
      "date": "2025-06-17",
      "price": 457.86
    },
    {
      "date": "2025-06-18",
      "price": 456.03
    },
    {
      "date": "2025-06-19",
      "price": 457.44
    },
    {
      "date": "2025-06-20",
      "price": 455.86
    },
    {
      "date": "2025-06-21",
      "price": 454.85
    },
    {
      "date": "2025-06-22",
      "price": 454.44
    }
  ],
  "intrinsicValueEstimates": [
    {
      "period": "Q1",
      "startDate": "2024-01-01",
      "endDate": "2024-03-31",
      "min": 440.07,
      "max": 462.54
    },
    {
      "period": "Q2",
      "startDate": "2024-04-01",
      "endDate": "2024-06-30",
      "min": 449.92,
      "max": 455.73
    },
    {
      "period": "Q3",
      "startDate": "2024-07-01",
      "endDate": "2024-09-30",
      "min": 431.72,
      "max": 471.69
    },
    {
      "period": "Q4",
      "startDate": "2024-10-01",
      "endDate": "2024-12-31",
      "min": 449.76,
      "max": 462.91
    }
  ],
  "evaluationMetrics": [
    {
      "name": "P/E",
      "description": "Price-to-Earnings Ratio",
      "values": [
        {
          "year": 2022,
          "value": 23.73,
          "label": "neutral"
        },
        {
          "year": 2023,
          "value": 31.44,
          "label": "bad"
        },
        {
          "year": 2024,
          "value": 33.285,
          "label": "bad"
        }
      ]
    },
    {
      "name": "ROE",
      "description": "Return on Equity",
      "values": [
        {
          "year": 2022,
          "value": 0.183,
          "label": "good"
        },
        {
          "year": 2023,
          "value": 0.196,
          "label": "good"
        },
        {
          "year": 2024,
          "value": 0.086,
          "label": "neutral"
        }
      ]
    },
    {
      "name": "Debt/Equity",
      "description": "Debt-to-Equity Ratio",
      "values": [
        {
          "year": 2022,
          "value": 1.016,
          "label": "neutral"
        },
        {
          "year": 2023,
          "value": 1.785,
          "label": "neutral"
        },
        {
          "year": 2024,
          "value": 2.426,
          "label": "bad"
        }
      ]
    },
    {
      "name": "Current Ratio",
      "description": "Current Assets / Current Liabilities",
      "values": [
        {
          "year": 2022,
          "value": 1.878,
          "label": "good"
        },
        {
          "year": 2023,
          "value": 2.291,
          "label": "good"
        },
        {
          "year": 2024,
          "value": 1.31,
          "label": "neutral"
        }
      ]
    },
    {
      "name": "Margin",
      "description": "Net Profit Margin",
      "values": [
        {
          "year": 2022,
          "value": 0.055,
          "label": "bad"
        },
        {
          "year": 2023,
          "value": 0.129,
          "label": "neutral"
        },
        {
          "year": 2024,
          "value": 0.158,
          "label": "neutral"
        }
      ]
    },
    {
      "name": "Beta",
      "description": "Volatility Compared to Market",
      "values": [
        {
          "year": 2022,
          "value": 1.556,
          "label": "bad"
        },
        {
          "year": 2023,
          "value": 1.786,
          "label": "bad"
        },
        {
          "year": 2024,
          "value": 0.946,
          "label": "good"
        }
      ]
    },
    {
      "name": "PBV",
      "description": "Price-to-Book Value",
      "values": [
        {
          "year": 2022,
          "value": 2.374,
          "label": "good"
        },
        {
          "year": 2023,
          "value": 5.763,
          "label": "bad"
        },
        {
          "year": 2024,
          "value": 7.224,
          "label": "bad"
        }
      ]
    },
    {
      "name": "Dividend Yield",
      "description": "Annual Dividends / Share Price",
      "values": [
        {
          "year": 2022,
          "value": 0.028,
          "label": "neutral"
        },
        {
          "year": 2023,
          "value": 0.018,
          "label": "neutral"
        },
        {
          "year": 2024,
          "value": 0.046,
          "label": "good"
        }
      ]
    }
  ]
}