{
  "companyName": "Soto, Mccall and Smith",
  "description": "Degree open team color. First nor piece already raise generation.\nDiscuss director parent. Really story peace good.\nWear threat TV information little may turn. Our state plant so figure.",
  "dailyStockPrice": [
    {
      "date": "2024-06-25",
      "price": 21.76
    },
    {
      "date": "2024-06-26",
      "price": 22.1
    },
    {
      "date": "2024-06-27",
      "price": 23.92
    },
    {
      "date": "2024-06-28",
      "price": 22.6
    },
    {
      "date": "2024-06-29",
      "price": 22.41
    },
    {
      "date": "2024-06-30",
      "price": 22.68
    },
    {
      "date": "2024-07-01",
      "price": 20.66
    },
    {
      "date": "2024-07-02",
      "price": 22.48
    },
    {
      "date": "2024-07-03",
      "price": 20.84
    },
    {
      "date": "2024-07-04",
      "price": 21.63
    },
    {
      "date": "2024-07-05",
      "price": 22.82
    },
    {
      "date": "2024-07-06",
      "price": 23.69
    },
    {
      "date": "2024-07-07",
      "price": 22.35
    },
    {
      "date": "2024-07-08",
      "price": 22.94
    },
    {
      "date": "2024-07-09",
      "price": 23.5
    },
    {
      "date": "2024-07-10",
      "price": 22.73
    },
    {
      "date": "2024-07-11",
      "price": 23.26
    },
    {
      "date": "2024-07-12",
      "price": 23.63
    },
    {
      "date": "2024-07-13",
      "price": 23.88
    },
    {
      "date": "2024-07-14",
      "price": 22.09
    },
    {
      "date": "2024-07-15",
      "price": 22.5
    },
    {
      "date": "2024-07-16",
      "price": 23.62
    },
    {
      "date": "2024-07-17",
      "price": 23.67
    },
    {
      "date": "2024-07-18",
      "price": 23.45
    },
    {
      "date": "2024-07-19",
      "price": 22.31
    },
    {
      "date": "2024-07-20",
      "price": 21.15
    },
    {
      "date": "2024-07-21",
      "price": 21.42
    },
    {
      "date": "2024-07-22",
      "price": 21.83
    },
    {
      "date": "2024-07-23",
      "price": 23.61
    },
    {
      "date": "2024-07-24",
      "price": 24.26
    },
    {
      "date": "2024-07-25",
      "price": 23.0
    },
    {
      "date": "2024-07-26",
      "price": 22.05
    },
    {
      "date": "2024-07-27",
      "price": 20.65
    },
    {
      "date": "2024-07-28",
      "price": 22.64
    },
    {
      "date": "2024-07-29",
      "price": 23.11
    },
    {
      "date": "2024-07-30",
      "price": 22.33
    },
    {
      "date": "2024-07-31",
      "price": 21.4
    },
    {
      "date": "2024-08-01",
      "price": 21.68
    },
    {
      "date": "2024-08-02",
      "price": 22.67
    },
    {
      "date": "2024-08-03",
      "price": 21.6
    },
    {
      "date": "2024-08-04",
      "price": 22.62
    },
    {
      "date": "2024-08-05",
      "price": 21.17
    },
    {
      "date": "2024-08-06",
      "price": 20.0
    },
    {
      "date": "2024-08-07",
      "price": 19.72
    },
    {
      "date": "2024-08-08",
      "price": 19.48
    },
    {
      "date": "2024-08-09",
      "price": 21.71
    },
    {
      "date": "2024-08-10",
      "price": 20.8
    },
    {
      "date": "2024-08-11",
      "price": 22.09
    },
    {
      "date": "2024-08-12",
      "price": 21.77
    },
    {
      "date": "2024-08-13",
      "price": 19.72
    },
    {
      "date": "2024-08-14",
      "price": 20.46
    },
    {
      "date": "2024-08-15",
      "price": 19.36
    },
    {
      "date": "2024-08-16",
      "price": 20.1
    },
    {
      "date": "2024-08-17",
      "price": 19.85
    },
    {
      "date": "2024-08-18",
      "price": 21.03
    },
    {
      "date": "2024-08-19",
      "price": 22.4
    },
    {
      "date": "2024-08-20",
      "price": 22.39
    },
    {
      "date": "2024-08-21",
      "price": 23.82
    },
    {
      "date": "2024-08-22",
      "price": 23.67
    },
    {
      "date": "2024-08-23",
      "price": 24.97
    },
    {
      "date": "2024-08-24",
      "price": 23.54
    },
    {
      "date": "2024-08-25",
      "price": 23.27
    },
    {
      "date": "2024-08-26",
      "price": 23.98
    },
    {
      "date": "2024-08-27",
      "price": 24.1
    },
    {
      "date": "2024-08-28",
      "price": 23.09
    },
    {
      "date": "2024-08-29",
      "price": 23.26
    },
    {
      "date": "2024-08-30",
      "price": 22.87
    },
    {
      "date": "2024-08-31",
      "price": 24.59
    },
    {
      "date": "2024-09-01",
      "price": 23.39
    },
    {
      "date": "2024-09-02",
      "price": 25.49
    },
    {
      "date": "2024-09-03",
      "price": 24.05
    },
    {
      "date": "2024-09-04",
      "price": 23.23
    },
    {
      "date": "2024-09-05",
      "price": 22.24
    },
    {
      "date": "2024-09-06",
      "price": 22.34
    },
    {
      "date": "2024-09-07",
      "price": 21.29
    },
    {
      "date": "2024-09-08",
      "price": 19.63
    },
    {
      "date": "2024-09-09",
      "price": 18.86
    },
    {
      "date": "2024-09-10",
      "price": 20.14
    },
    {
      "date": "2024-09-11",
      "price": 19.93
    },
    {
      "date": "2024-09-12",
      "price": 18.33
    },
    {
      "date": "2024-09-13",
      "price": 18.99
    },
    {
      "date": "2024-09-14",
      "price": 20.42
    },
    {
      "date": "2024-09-15",
      "price": 19.91
    },
    {
      "date": "2024-09-16",
      "price": 19.81
    },
    {
      "date": "2024-09-17",
      "price": 20.44
    },
    {
      "date": "2024-09-18",
      "price": 21.67
    },
    {
      "date": "2024-09-19",
      "price": 20.34
    },
    {
      "date": "2024-09-20",
      "price": 19.54
    },
    {
      "date": "2024-09-21",
      "price": 20.0
    },
    {
      "date": "2024-09-22",
      "price": 19.79
    },
    {
      "date": "2024-09-23",
      "price": 17.79
    },
    {
      "date": "2024-09-24",
      "price": 19.01
    },
    {
      "date": "2024-09-25",
      "price": 17.43
    },
    {
      "date": "2024-09-26",
      "price": 19.1
    },
    {
      "date": "2024-09-27",
      "price": 17.31
    },
    {
      "date": "2024-09-28",
      "price": 17.91
    },
    {
      "date": "2024-09-29",
      "price": 18.84
    },
    {
      "date": "2024-09-30",
      "price": 20.71
    },
    {
      "date": "2024-10-01",
      "price": 19.97
    },
    {
      "date": "2024-10-02",
      "price": 20.28
    },
    {
      "date": "2024-10-03",
      "price": 19.91
    },
    {
      "date": "2024-10-04",
      "price": 21.96
    },
    {
      "date": "2024-10-05",
      "price": 22.95
    },
    {
      "date": "2024-10-06",
      "price": 22.72
    },
    {
      "date": "2024-10-07",
      "price": 24.55
    },
    {
      "date": "2024-10-08",
      "price": 24.43
    },
    {
      "date": "2024-10-09",
      "price": 25.03
    },
    {
      "date": "2024-10-10",
      "price": 24.45
    },
    {
      "date": "2024-10-11",
      "price": 25.58
    },
    {
      "date": "2024-10-12",
      "price": 25.5
    },
    {
      "date": "2024-10-13",
      "price": 26.03
    },
    {
      "date": "2024-10-14",
      "price": 26.23
    },
    {
      "date": "2024-10-15",
      "price": 25.56
    },
    {
      "date": "2024-10-16",
      "price": 26.05
    },
    {
      "date": "2024-10-17",
      "price": 27.05
    },
    {
      "date": "2024-10-18",
      "price": 25.26
    },
    {
      "date": "2024-10-19",
      "price": 24.79
    },
    {
      "date": "2024-10-20",
      "price": 24.13
    },
    {
      "date": "2024-10-21",
      "price": 24.32
    },
    {
      "date": "2024-10-22",
      "price": 25.53
    },
    {
      "date": "2024-10-23",
      "price": 25.97
    },
    {
      "date": "2024-10-24",
      "price": 24.67
    },
    {
      "date": "2024-10-25",
      "price": 23.36
    },
    {
      "date": "2024-10-26",
      "price": 23.95
    },
    {
      "date": "2024-10-27",
      "price": 24.53
    },
    {
      "date": "2024-10-28",
      "price": 24.5
    },
    {
      "date": "2024-10-29",
      "price": 23.45
    },
    {
      "date": "2024-10-30",
      "price": 21.2
    },
    {
      "date": "2024-10-31",
      "price": 21.61
    },
    {
      "date": "2024-11-01",
      "price": 22.65
    },
    {
      "date": "2024-11-02",
      "price": 23.07
    },
    {
      "date": "2024-11-03",
      "price": 22.27
    },
    {
      "date": "2024-11-04",
      "price": 23.54
    },
    {
      "date": "2024-11-05",
      "price": 23.09
    },
    {
      "date": "2024-11-06",
      "price": 22.9
    },
    {
      "date": "2024-11-07",
      "price": 22.7
    },
    {
      "date": "2024-11-08",
      "price": 22.37
    },
    {
      "date": "2024-11-09",
      "price": 22.38
    },
    {
      "date": "2024-11-10",
      "price": 23.7
    },
    {
      "date": "2024-11-11",
      "price": 24.69
    },
    {
      "date": "2024-11-12",
      "price": 26.84
    },
    {
      "date": "2024-11-13",
      "price": 27.45
    },
    {
      "date": "2024-11-14",
      "price": 28.82
    },
    {
      "date": "2024-11-15",
      "price": 28.12
    },
    {
      "date": "2024-11-16",
      "price": 26.87
    },
    {
      "date": "2024-11-17",
      "price": 27.05
    },
    {
      "date": "2024-11-18",
      "price": 27.9
    },
    {
      "date": "2024-11-19",
      "price": 28.55
    },
    {
      "date": "2024-11-20",
      "price": 30.22
    },
    {
      "date": "2024-11-21",
      "price": 29.26
    },
    {
      "date": "2024-11-22",
      "price": 29.99
    },
    {
      "date": "2024-11-23",
      "price": 28.89
    },
    {
      "date": "2024-11-24",
      "price": 29.04
    },
    {
      "date": "2024-11-25",
      "price": 28.46
    },
    {
      "date": "2024-11-26",
      "price": 29.5
    },
    {
      "date": "2024-11-27",
      "price": 30.49
    },
    {
      "date": "2024-11-28",
      "price": 30.28
    },
    {
      "date": "2024-11-29",
      "price": 31.73
    },
    {
      "date": "2024-11-30",
      "price": 31.52
    },
    {
      "date": "2024-12-01",
      "price": 31.23
    },
    {
      "date": "2024-12-02",
      "price": 32.01
    },
    {
      "date": "2024-12-03",
      "price": 31.39
    },
    {
      "date": "2024-12-04",
      "price": 32.01
    },
    {
      "date": "2024-12-05",
      "price": 31.43
    },
    {
      "date": "2024-12-06",
      "price": 30.77
    },
    {
      "date": "2024-12-07",
      "price": 30.84
    },
    {
      "date": "2024-12-08",
      "price": 30.83
    },
    {
      "date": "2024-12-09",
      "price": 30.49
    },
    {
      "date": "2024-12-10",
      "price": 32.29
    },
    {
      "date": "2024-12-11",
      "price": 32.3
    },
    {
      "date": "2024-12-12",
      "price": 31.34
    },
    {
      "date": "2024-12-13",
      "price": 30.27
    },
    {
      "date": "2024-12-14",
      "price": 31.84
    },
    {
      "date": "2024-12-15",
      "price": 31.24
    },
    {
      "date": "2024-12-16",
      "price": 31.43
    },
    {
      "date": "2024-12-17",
      "price": 30.01
    },
    {
      "date": "2024-12-18",
      "price": 30.5
    },
    {
      "date": "2024-12-19",
      "price": 30.73
    },
    {
      "date": "2024-12-20",
      "price": 29.57
    },
    {
      "date": "2024-12-21",
      "price": 31.21
    },
    {
      "date": "2024-12-22",
      "price": 30.93
    },
    {
      "date": "2024-12-23",
      "price": 32.22
    },
    {
      "date": "2024-12-24",
      "price": 31.32
    },
    {
      "date": "2024-12-25",
      "price": 29.8
    },
    {
      "date": "2024-12-26",
      "price": 30.87
    },
    {
      "date": "2024-12-27",
      "price": 31.9
    },
    {
      "date": "2024-12-28",
      "price": 31.83
    },
    {
      "date": "2024-12-29",
      "price": 33.45
    },
    {
      "date": "2024-12-30",
      "price": 34.89
    },
    {
      "date": "2024-12-31",
      "price": 33.06
    },
    {
      "date": "2025-01-01",
      "price": 33.58
    },
    {
      "date": "2025-01-02",
      "price": 34.74
    },
    {
      "date": "2025-01-03",
      "price": 36.53
    },
    {
      "date": "2025-01-04",
      "price": 35.5
    },
    {
      "date": "2025-01-05",
      "price": 35.03
    },
    {
      "date": "2025-01-06",
      "price": 34.97
    },
    {
      "date": "2025-01-07",
      "price": 35.59
    },
    {
      "date": "2025-01-08",
      "price": 35.99
    },
    {
      "date": "2025-01-09",
      "price": 36.73
    },
    {
      "date": "2025-01-10",
      "price": 35.99
    },
    {
      "date": "2025-01-11",
      "price": 37.31
    },
    {
      "date": "2025-01-12",
      "price": 38.93
    },
    {
      "date": "2025-01-13",
      "price": 38.05
    },
    {
      "date": "2025-01-14",
      "price": 37.43
    },
    {
      "date": "2025-01-15",
      "price": 36.43
    },
    {
      "date": "2025-01-16",
      "price": 37.18
    },
    {
      "date": "2025-01-17",
      "price": 37.25
    },
    {
      "date": "2025-01-18",
      "price": 35.44
    },
    {
      "date": "2025-01-19",
      "price": 34.47
    },
    {
      "date": "2025-01-20",
      "price": 35.89
    },
    {
      "date": "2025-01-21",
      "price": 34.98
    },
    {
      "date": "2025-01-22",
      "price": 35.2
    },
    {
      "date": "2025-01-23",
      "price": 34.17
    },
    {
      "date": "2025-01-24",
      "price": 34.16
    },
    {
      "date": "2025-01-25",
      "price": 35.62
    },
    {
      "date": "2025-01-26",
      "price": 34.33
    },
    {
      "date": "2025-01-27",
      "price": 35.64
    },
    {
      "date": "2025-01-28",
      "price": 35.8
    },
    {
      "date": "2025-01-29",
      "price": 35.43
    },
    {
      "date": "2025-01-30",
      "price": 34.24
    },
    {
      "date": "2025-01-31",
      "price": 35.1
    },
    {
      "date": "2025-02-01",
      "price": 34.55
    },
    {
      "date": "2025-02-02",
      "price": 33.97
    },
    {
      "date": "2025-02-03",
      "price": 33.41
    },
    {
      "date": "2025-02-04",
      "price": 33.82
    },
    {
      "date": "2025-02-05",
      "price": 32.97
    },
    {
      "date": "2025-02-06",
      "price": 34.49
    },
    {
      "date": "2025-02-07",
      "price": 32.89
    },
    {
      "date": "2025-02-08",
      "price": 32.24
    },
    {
      "date": "2025-02-09",
      "price": 32.21
    },
    {
      "date": "2025-02-10",
      "price": 31.48
    },
    {
      "date": "2025-02-11",
      "price": 31.12
    },
    {
      "date": "2025-02-12",
      "price": 30.82
    },
    {
      "date": "2025-02-13",
      "price": 32.17
    },
    {
      "date": "2025-02-14",
      "price": 31.98
    },
    {
      "date": "2025-02-15",
      "price": 31.82
    },
    {
      "date": "2025-02-16",
      "price": 32.97
    },
    {
      "date": "2025-02-17",
      "price": 33.85
    },
    {
      "date": "2025-02-18",
      "price": 33.01
    },
    {
      "date": "2025-02-19",
      "price": 32.66
    },
    {
      "date": "2025-02-20",
      "price": 30.81
    },
    {
      "date": "2025-02-21",
      "price": 30.19
    },
    {
      "date": "2025-02-22",
      "price": 28.43
    },
    {
      "date": "2025-02-23",
      "price": 28.6
    },
    {
      "date": "2025-02-24",
      "price": 29.44
    },
    {
      "date": "2025-02-25",
      "price": 30.43
    },
    {
      "date": "2025-02-26",
      "price": 29.73
    },
    {
      "date": "2025-02-27",
      "price": 30.77
    },
    {
      "date": "2025-02-28",
      "price": 31.74
    },
    {
      "date": "2025-03-01",
      "price": 32.85
    },
    {
      "date": "2025-03-02",
      "price": 31.98
    },
    {
      "date": "2025-03-03",
      "price": 32.21
    },
    {
      "date": "2025-03-04",
      "price": 31.68
    },
    {
      "date": "2025-03-05",
      "price": 30.61
    },
    {
      "date": "2025-03-06",
      "price": 29.88
    },
    {
      "date": "2025-03-07",
      "price": 28.78
    },
    {
      "date": "2025-03-08",
      "price": 29.61
    },
    {
      "date": "2025-03-09",
      "price": 30.94
    },
    {
      "date": "2025-03-10",
      "price": 29.93
    },
    {
      "date": "2025-03-11",
      "price": 31.58
    },
    {
      "date": "2025-03-12",
      "price": 31.97
    },
    {
      "date": "2025-03-13",
      "price": 31.74
    },
    {
      "date": "2025-03-14",
      "price": 32.49
    },
    {
      "date": "2025-03-15",
      "price": 32.01
    },
    {
      "date": "2025-03-16",
      "price": 30.92
    },
    {
      "date": "2025-03-17",
      "price": 30.37
    },
    {
      "date": "2025-03-18",
      "price": 30.3
    },
    {
      "date": "2025-03-19",
      "price": 30.44
    },
    {
      "date": "2025-03-20",
      "price": 30.19
    },
    {
      "date": "2025-03-21",
      "price": 30.46
    },
    {
      "date": "2025-03-22",
      "price": 30.54
    },
    {
      "date": "2025-03-23",
      "price": 29.89
    },
    {
      "date": "2025-03-24",
      "price": 30.31
    },
    {
      "date": "2025-03-25",
      "price": 30.36
    },
    {
      "date": "2025-03-26",
      "price": 29.29
    },
    {
      "date": "2025-03-27",
      "price": 29.95
    },
    {
      "date": "2025-03-28",
      "price": 29.58
    },
    {
      "date": "2025-03-29",
      "price": 29.49
    },
    {
      "date": "2025-03-30",
      "price": 29.5
    },
    {
      "date": "2025-03-31",
      "price": 27.59
    },
    {
      "date": "2025-04-01",
      "price": 27.07
    },
    {
      "date": "2025-04-02",
      "price": 26.92
    },
    {
      "date": "2025-04-03",
      "price": 27.47
    },
    {
      "date": "2025-04-04",
      "price": 28.12
    },
    {
      "date": "2025-04-05",
      "price": 27.25
    },
    {
      "date": "2025-04-06",
      "price": 27.22
    },
    {
      "date": "2025-04-07",
      "price": 28.5
    },
    {
      "date": "2025-04-08",
      "price": 29.22
    },
    {
      "date": "2025-04-09",
      "price": 28.47
    },
    {
      "date": "2025-04-10",
      "price": 27.34
    },
    {
      "date": "2025-04-11",
      "price": 28.68
    },
    {
      "date": "2025-04-12",
      "price": 28.58
    },
    {
      "date": "2025-04-13",
      "price": 26.78
    },
    {
      "date": "2025-04-14",
      "price": 27.9
    },
    {
      "date": "2025-04-15",
      "price": 27.7
    },
    {
      "date": "2025-04-16",
      "price": 27.79
    },
    {
      "date": "2025-04-17",
      "price": 27.03
    },
    {
      "date": "2025-04-18",
      "price": 27.04
    },
    {
      "date": "2025-04-19",
      "price": 26.15
    },
    {
      "date": "2025-04-20",
      "price": 25.87
    },
    {
      "date": "2025-04-21",
      "price": 27.41
    },
    {
      "date": "2025-04-22",
      "price": 25.92
    },
    {
      "date": "2025-04-23",
      "price": 27.07
    },
    {
      "date": "2025-04-24",
      "price": 25.15
    },
    {
      "date": "2025-04-25",
      "price": 25.18
    },
    {
      "date": "2025-04-26",
      "price": 26.28
    },
    {
      "date": "2025-04-27",
      "price": 27.45
    },
    {
      "date": "2025-04-28",
      "price": 27.69
    },
    {
      "date": "2025-04-29",
      "price": 28.58
    },
    {
      "date": "2025-04-30",
      "price": 26.72
    },
    {
      "date": "2025-05-01",
      "price": 25.77
    },
    {
      "date": "2025-05-02",
      "price": 27.14
    },
    {
      "date": "2025-05-03",
      "price": 26.61
    },
    {
      "date": "2025-05-04",
      "price": 25.0
    },
    {
      "date": "2025-05-05",
      "price": 24.21
    },
    {
      "date": "2025-05-06",
      "price": 23.5
    },
    {
      "date": "2025-05-07",
      "price": 23.47
    },
    {
      "date": "2025-05-08",
      "price": 23.48
    },
    {
      "date": "2025-05-09",
      "price": 22.15
    },
    {
      "date": "2025-05-10",
      "price": 21.02
    },
    {
      "date": "2025-05-11",
      "price": 21.59
    },
    {
      "date": "2025-05-12",
      "price": 22.49
    },
    {
      "date": "2025-05-13",
      "price": 23.21
    },
    {
      "date": "2025-05-14",
      "price": 23.48
    },
    {
      "date": "2025-05-15",
      "price": 25.59
    },
    {
      "date": "2025-05-16",
      "price": 26.15
    },
    {
      "date": "2025-05-17",
      "price": 24.94
    },
    {
      "date": "2025-05-18",
      "price": 24.04
    },
    {
      "date": "2025-05-19",
      "price": 24.23
    },
    {
      "date": "2025-05-20",
      "price": 25.85
    },
    {
      "date": "2025-05-21",
      "price": 24.71
    },
    {
      "date": "2025-05-22",
      "price": 23.24
    },
    {
      "date": "2025-05-23",
      "price": 22.75
    },
    {
      "date": "2025-05-24",
      "price": 21.85
    },
    {
      "date": "2025-05-25",
      "price": 20.42
    },
    {
      "date": "2025-05-26",
      "price": 21.0
    },
    {
      "date": "2025-05-27",
      "price": 21.76
    },
    {
      "date": "2025-05-28",
      "price": 21.3
    },
    {
      "date": "2025-05-29",
      "price": 21.64
    },
    {
      "date": "2025-05-30",
      "price": 20.77
    },
    {
      "date": "2025-05-31",
      "price": 21.68
    },
    {
      "date": "2025-06-01",
      "price": 20.63
    },
    {
      "date": "2025-06-02",
      "price": 21.48
    },
    {
      "date": "2025-06-03",
      "price": 21.15
    },
    {
      "date": "2025-06-04",
      "price": 22.29
    },
    {
      "date": "2025-06-05",
      "price": 22.43
    },
    {
      "date": "2025-06-06",
      "price": 21.93
    },
    {
      "date": "2025-06-07",
      "price": 21.24
    },
    {
      "date": "2025-06-08",
      "price": 21.88
    },
    {
      "date": "2025-06-09",
      "price": 22.16
    },
    {
      "date": "2025-06-10",
      "price": 20.39
    },
    {
      "date": "2025-06-11",
      "price": 21.53
    },
    {
      "date": "2025-06-12",
      "price": 21.21
    },
    {
      "date": "2025-06-13",
      "price": 20.86
    },
    {
      "date": "2025-06-14",
      "price": 20.68
    },
    {
      "date": "2025-06-15",
      "price": 22.42
    },
    {
      "date": "2025-06-16",
      "price": 24.01
    },
    {
      "date": "2025-06-17",
      "price": 22.11
    },
    {
      "date": "2025-06-18",
      "price": 21.35
    },
    {
      "date": "2025-06-19",
      "price": 21.45
    },
    {
      "date": "2025-06-20",
      "price": 20.21
    },
    {
      "date": "2025-06-21",
      "price": 21.1
    },
    {
      "date": "2025-06-22",
      "price": 22.14
    },
    {
      "date": "2025-06-23",
      "price": 21.05
    },
    {
      "date": "2025-06-24",
      "price": 20.63
    }
  ],
  "intrinsicValueEstimates": [
    {
      "period": "Q1",
      "startDate": "2024-01-01",
      "endDate": "2024-04-01",
      "min": 25.49,
      "max": 26.88
    },
    {
      "period": "Q2",
      "startDate": "2024-04-01",
      "endDate": "2024-07-01",
      "min": 25.36,
      "max": 27.68
    },
    {
      "period": "Q3",
      "startDate": "2024-07-01",
      "endDate": "2024-10-01",
      "min": 25.33,
      "max": 27.18
    },
    {
      "period": "Q4",
      "startDate": "2024-10-01",
      "endDate": "2025-01-01",
      "min": 25.75,
      "max": 26.84
    },
    {
      "period": "Q5",
      "startDate": "2025-01-01",
      "endDate": "2025-04-01",
      "min": 25.78,
      "max": 27.42
    },
    {
      "period": "Q6",
      "startDate": "2025-04-01",
      "endDate": "2025-06-30",
      "min": 25.89,
      "max": 27.29
    }
  ],
  "evaluationMetrics": [
    {
      "name": "P/E",
      "description": "Price-to-Earnings Ratio",
      "values": [
        {
          "year": 2022,
          "value": 22.108,
          "label": "neutral"
        },
        {
          "year": 2023,
          "value": 23.638,
          "label": "neutral"
        },
        {
          "year": 2024,
          "value": 32.813,
          "label": "bad"
        }
      ]
    },
    {
      "name": "ROE",
      "description": "Return on Equity",
      "values": [
        {
          "year": 2022,
          "value": 0.219,
          "label": "good"
        },
        {
          "year": 2023,
          "value": 0.103,
          "label": "neutral"
        },
        {
          "year": 2024,
          "value": 0.122,
          "label": "neutral"
        }
      ]
    },
    {
      "name": "Debt/Equity",
      "description": "Debt-to-Equity Ratio",
      "values": [
        {
          "year": 2022,
          "value": 2.785,
          "label": "bad"
        },
        {
          "year": 2023,
          "value": 0.47,
          "label": "good"
        },
        {
          "year": 2024,
          "value": 1.109,
          "label": "neutral"
        }
      ]
    },
    {
      "name": "Current Ratio",
      "description": "Current Assets / Current Liabilities",
      "values": [
        {
          "year": 2022,
          "value": 1.881,
          "label": "good"
        },
        {
          "year": 2023,
          "value": 1.268,
          "label": "neutral"
        },
        {
          "year": 2024,
          "value": 1.614,
          "label": "good"
        }
      ]
    },
    {
      "name": "Margin",
      "description": "Net Profit Margin",
      "values": [
        {
          "year": 2022,
          "value": 0.1,
          "label": "bad"
        },
        {
          "year": 2023,
          "value": 0.203,
          "label": "good"
        },
        {
          "year": 2024,
          "value": 0.059,
          "label": "bad"
        }
      ]
    },
    {
      "name": "Beta",
      "description": "Volatility Compared to Market",
      "values": [
        {
          "year": 2022,
          "value": 1.587,
          "label": "bad"
        },
        {
          "year": 2023,
          "value": 0.891,
          "label": "good"
        },
        {
          "year": 2024,
          "value": 1.457,
          "label": "bad"
        }
      ]
    },
    {
      "name": "PBV",
      "description": "Price-to-Book Value",
      "values": [
        {
          "year": 2022,
          "value": 3.544,
          "label": "neutral"
        },
        {
          "year": 2023,
          "value": 2.303,
          "label": "good"
        },
        {
          "year": 2024,
          "value": 6.633,
          "label": "bad"
        }
      ]
    },
    {
      "name": "Dividend Yield",
      "description": "Annual Dividends / Share Price",
      "values": [
        {
          "year": 2022,
          "value": 0.011,
          "label": "neutral"
        },
        {
          "year": 2023,
          "value": 0.012,
          "label": "neutral"
        },
        {
          "year": 2024,
          "value": 0.013,
          "label": "neutral"
        }
      ]
    }
  ]
}